{
  "_id": "a06e199fd85708c7",
  "name": "Masking (Rating 5)",
  "type": "program",
  "img": "icons/magic/perception/eye-ringed-green.webp",
  "system": {
    "category": "masking",
    "rating": 5,
    "size": 7.5,
    "multiplier": 1.5,
    "cost": 30000,
    "loaded": false,
    "notes": "SR2E p.262. Persona program: Matrix masking capability. Rating 5."
  },
  "effects": [],
  "flags": {},
  "_stats": {
    "coreVersion": "13.351",
    "systemId": "sr2e",
    "systemVersion": "0.3.7",
    "createdTime": 1700000000000,
    "modifiedTime": 1700000000000,
    "lastModifiedBy": null,
    "compendiumSource": null,
    "duplicateSource": null,
    "exportSource": null
  },
  "folder": null,
  "sort": 0,
  "ownership": {
    "default": 0
  },
  "_key": "!items!a06e199fd85708c7"
}
